think/__init__.py
think/core/__init__.py
think/core/agent.py
think/core/analysis.py
think/core/item.py
think/core/process.py
think/core/test_agent.py
think/core/test_item.py
think/modules/__init__.py
think/modules/memory/__init__.py
think/modules/memory/memory.py
think/modules/memory/test_memory.py
think/modules/motor/__init__.py
think/modules/motor/motor.py
think/modules/motor/test_motor.py
think/modules/speech/__init__.py
think/modules/speech/speech.py
think/modules/speech/test_speech.py
think/modules/vision/__init__.py
think/modules/vision/test_vision.py
think/modules/vision/vision.py
think/skills/__init__.py
think/skills/arithmetic/__init__.py
think/skills/arithmetic/arithmetic.py
think/skills/arithmetic/test_arithmetic.py
thinkpy-0.0.1.dev3.dist-info/LICENSE.txt
thinkpy-0.0.1.dev3.dist-info/METADATA
thinkpy-0.0.1.dev3.dist-info/RECORD
thinkpy-0.0.1.dev3.dist-info/WHEEL
thinkpy-0.0.1.dev3.dist-info/top_level.txt
