Metadata-Version: 2.1
Name: thinkpy
Version: 0.0.1.dev3
Summary: A cognitive-code architecture in Python
Home-page: UNKNOWN
Author: Dario Salvucci
Author-email: 233049+salvucci@users.noreply.github.com
License: UNKNOWN
Keywords: think cognitive architecture cognitive code
Platform: UNKNOWN
Classifier: Development Status :: 3 - Alpha
Classifier: Intended Audience :: Developers
Classifier: Topic :: Software Development :: Build Tools
Classifier: License :: OSI Approved :: MIT License
Classifier: Programming Language :: Python :: 3.2
Classifier: Programming Language :: Python :: 3.3
Classifier: Programming Language :: Python :: 3.4
Classifier: Programming Language :: Python :: 3.5
Classifier: Programming Language :: Python :: 3.6
